MANIFEST.in
README.md
init.sh
setup.py
Hacker/__init__.py
Hacker/ini/TEMPLATES.py
Hacker/ini/__init__.py
Hacker/ini/settings.py
Hacker/libs/__init__.py
Hacker/libs/cmd.py
Hacker/libs/hackerlib.py
Hacker/libs/networklib.py
Hacker/libs/socialdatalib.py
Hacker/modules/Code.py
Hacker/modules/Social.py
Hacker/modules/TableW.py
Hacker/modules/U.py
Hacker/modules/__init__.py
Hacker/res/default.ini
Hacker/res/U/ASP.txt
Hacker/res/U/ASPX.txt
Hacker/res/U/DIR.txt
Hacker/res/U/JSP.txt
Hacker/res/U/MDB.txt
Hacker/res/U/PHP.txt
Hacker/res/U/cgi.txt
hackcmds.egg-info/PKG-INFO
hackcmds.egg-info/SOURCES.txt
hackcmds.egg-info/dependency_links.txt
hackcmds.egg-info/entry_points.txt
hackcmds.egg-info/not-zip-safe
hackcmds.egg-info/requires.txt
hackcmds.egg-info/top_level.txt