Metadata-Version: 1.0
Name: hackcmds
Version: 5.2
Summary: fix bug, add table scrap
Home-page: https://github.com/Qingluan/.git
Author: Qing luan
Author-email: darkhackdevil@gmail.com
License: MIT
Platform: UNKNOWN
